{
  "project_info": {
    "project_number": "627666588793",
    "project_id": "estudai-65d8b",
    "storage_bucket": "estudai-65d8b.firebasestorage.app"
  },
  "client": [
    {
      "client_info": {
        "mobilesdk_app_id": "1:627666588793:android:15c5c2ec0cd644d6c470a8",
        "android_client_info": {
          "package_name": "com.estudai"
        }
      },
      "oauth_client": [
        {
          "client_id": "627666588793-mbvvc3rqi13she11nk6tbolksdjgea4u.apps.googleusercontent.com",
          "client_type": 1,
          "android_info": {
            "package_name": "com.estudai",
            "certificate_hash": "5fe297be661ed2d68e1cdf2a54ff5f8695f17772"
          }
        },
        {
          "client_id": "627666588793-6c964g40sccgjvue1f00d0jm2bbitsrk.apps.googleusercontent.com",
          "client_type": 3
        }
      ],
      "api_key": [
        {
          "current_key": "AIzaSyCcPRmoqYT4XInF-sO7OIUzxAOVx89oL2Y"
        }
      ],
      "services": {
        "appinvite_service": {
          "other_platform_oauth_client": [
            {
              "client_id": "627666588793-6c964g40sccgjvue1f00d0jm2bbitsrk.apps.googleusercontent.com",
              "client_type": 3
            }
          ]
        }
      }
    }
  ],
  "configuration_version": "1"
}